peaq/__init__.py
peaq/did.py
peaq/eth.py
peaq/extrinsic.py
peaq/rbac.py
peaq/storage.py
peaq/sudo_extrinsic.py
peaq/utils.py
peaq_py-0.2.6.dist-info/LICENSE
peaq_py-0.2.6.dist-info/METADATA
peaq_py-0.2.6.dist-info/WHEEL
peaq_py-0.2.6.dist-info/top_level.txt
peaq_py-0.2.6.dist-info/RECORD
