Metadata-Version: 2.1
Name: peaq-py
Version: 0.2.6
Summary: peaq python sdk
Home-page: https://github.com/peaqnetwork/peaq-py/
Author: Jay Pan
Author-email: pan@eotlabs.io
License-File: LICENSE
